README.rst
setup.cfg
setup.py
haka_mqtt/__init__.py
haka_mqtt/clock.py
haka_mqtt/cycle_iter.py
haka_mqtt/dns_async.py
haka_mqtt/dns_sync.py
haka_mqtt/exception.py
haka_mqtt/mqtt_request.py
haka_mqtt/null_log.py
haka_mqtt/on_str.py
haka_mqtt/packet_ids.py
haka_mqtt/reactor.py
haka_mqtt/scheduler.py
haka_mqtt/selector.py
haka_mqtt/socket_factory.py
haka_mqtt.egg-info/PKG-INFO
haka_mqtt.egg-info/SOURCES.txt
haka_mqtt.egg-info/dependency_links.txt
haka_mqtt.egg-info/requires.txt
haka_mqtt.egg-info/top_level.txt
haka_mqtt/frontends/__init__.py
haka_mqtt/frontends/event_queue.py
haka_mqtt/frontends/poll.py
scripts/mqtt-sub.py