Metadata-Version: 2.1
Name: haka-mqtt
Version: 0.3.5
Summary: Weapons grade MQTT client.
Home-page: https://github.com/kcallin/haka-mqtt
Author: Keegan Callin
Author-email: kc@kcallin.net
License: UNKNOWN
Project-URL: Bug Tracker, https://github.com/kcallin/haka-mqtt/issues
Project-URL: Documentation, https://haka-mqtt.readthedocs.io/en/latest/
Project-URL: Source Code, https://github.com/kcallin/haka-mqtt
Platform: UNKNOWN
Classifier: Development Status :: 4 - Beta
Classifier: Intended Audience :: Developers
Classifier: Topic :: Communications
Classifier: Topic :: Internet
Classifier: Topic :: Software Development
Classifier: Topic :: Software Development :: Libraries
Classifier: Topic :: Software Development :: Libraries :: Python Modules
Classifier: Programming Language :: Python
Classifier: Programming Language :: Python :: 2
Classifier: Programming Language :: Python :: 2.7
Classifier: Programming Language :: Python :: 3
Classifier: Programming Language :: Python :: 3.4
Classifier: Programming Language :: Python :: 3.5
Classifier: Programming Language :: Python :: 3.6
Classifier: Programming Language :: Python :: 3.7
Classifier: License :: OSI Approved :: GNU Lesser General Public License v3 (LGPLv3)
Classifier: Operating System :: POSIX :: Linux
Requires-Python: >=2.7
